docs/source/conf.py
gfdlvitals/__init__.py
gfdlvitals/cli.py
gfdlvitals/extensions.py
gfdlvitals/plot.py
gfdlvitals/sample.py
gfdlvitals/version.py
gfdlvitals/averagers/__init__.py
gfdlvitals/averagers/cubesphere.py
gfdlvitals/averagers/ice.py
gfdlvitals/averagers/land_lm3.py
gfdlvitals/averagers/land_lm4.py
gfdlvitals/averagers/latlon.py
gfdlvitals/averagers/tripolar.py
gfdlvitals/diags/__init__.py
gfdlvitals/diags/amoc.py
gfdlvitals/diags/fms.py
gfdlvitals/diags/m6toolbox.py
gfdlvitals/models/CM4.py
gfdlvitals/models/ESM2.py
gfdlvitals/models/__init__.py
gfdlvitals/resources/LM3_variable_dictionary.pkl
gfdlvitals/resources/historical.db
gfdlvitals/resources/picontrol.db
gfdlvitals/resources/fonts/Roboto/LICENSE.txt
gfdlvitals/resources/fonts/Roboto/Roboto-Black.ttf
gfdlvitals/resources/fonts/Roboto/Roboto-BlackItalic.ttf
gfdlvitals/resources/fonts/Roboto/Roboto-Bold.ttf
gfdlvitals/resources/fonts/Roboto/Roboto-BoldItalic.ttf
gfdlvitals/resources/fonts/Roboto/Roboto-Italic.ttf
gfdlvitals/resources/fonts/Roboto/Roboto-Light.ttf
gfdlvitals/resources/fonts/Roboto/Roboto-LightItalic.ttf
gfdlvitals/resources/fonts/Roboto/Roboto-Medium.ttf
gfdlvitals/resources/fonts/Roboto/Roboto-MediumItalic.ttf
gfdlvitals/resources/fonts/Roboto/Roboto-Regular.ttf
gfdlvitals/resources/fonts/Roboto/Roboto-Thin.ttf
gfdlvitals/resources/fonts/Roboto/Roboto-ThinItalic.ttf
gfdlvitals/resources/fonts/Roboto_Condensed/LICENSE.txt
gfdlvitals/resources/fonts/Roboto_Condensed/RobotoCondensed-Bold.ttf
gfdlvitals/resources/fonts/Roboto_Condensed/RobotoCondensed-BoldItalic.ttf
gfdlvitals/resources/fonts/Roboto_Condensed/RobotoCondensed-Italic.ttf
gfdlvitals/resources/fonts/Roboto_Condensed/RobotoCondensed-Light.ttf
gfdlvitals/resources/fonts/Roboto_Condensed/RobotoCondensed-LightItalic.ttf
gfdlvitals/resources/fonts/Roboto_Condensed/RobotoCondensed-Regular.ttf
gfdlvitals/util/__init__.py
gfdlvitals/util/average.py
gfdlvitals/util/extract_ocean_scalar.py
gfdlvitals/util/git.py
gfdlvitals-3.0.11.dist-info/LICENSE
gfdlvitals-3.0.11.dist-info/METADATA
gfdlvitals-3.0.11.dist-info/WHEEL
gfdlvitals-3.0.11.dist-info/top_level.txt
gfdlvitals-3.0.11.dist-info/RECORD
